concrete/__init__.py
concrete/inspect.py
concrete/validate.py
concrete/version.py
concrete/access/FetchCommunicationService.py
concrete/access/StoreCommunicationService.py
concrete/access/__init__.py
concrete/access/constants.py
concrete/access/ttypes.py
concrete/annotate/AnnotateCommunicationBatchService.py
concrete/annotate/AnnotateCommunicationService.py
concrete/annotate/AnnotateWithContextService.py
concrete/annotate/__init__.py
concrete/annotate/constants.py
concrete/annotate/ttypes.py
concrete/audio/__init__.py
concrete/audio/constants.py
concrete/audio/ttypes.py
concrete/clustering/__init__.py
concrete/clustering/constants.py
concrete/clustering/ttypes.py
concrete/communication/__init__.py
concrete/communication/constants.py
concrete/communication/ttypes.py
concrete/context/__init__.py
concrete/context/constants.py
concrete/context/ttypes.py
concrete/convert/ConvertCommunicationService.py
concrete/convert/__init__.py
concrete/convert/constants.py
concrete/convert/ttypes.py
concrete/email/__init__.py
concrete/email/constants.py
concrete/email/ttypes.py
concrete/entities/__init__.py
concrete/entities/constants.py
concrete/entities/ttypes.py
concrete/exceptions/__init__.py
concrete/exceptions/constants.py
concrete/exceptions/ttypes.py
concrete/language/__init__.py
concrete/language/constants.py
concrete/language/ttypes.py
concrete/learn/ActiveLearnerClientService.py
concrete/learn/ActiveLearnerServerService.py
concrete/learn/__init__.py
concrete/learn/constants.py
concrete/learn/ttypes.py
concrete/linking/__init__.py
concrete/linking/constants.py
concrete/linking/ttypes.py
concrete/metadata/__init__.py
concrete/metadata/constants.py
concrete/metadata/ttypes.py
concrete/nitf/__init__.py
concrete/nitf/constants.py
concrete/nitf/ttypes.py
concrete/property/__init__.py
concrete/property/constants.py
concrete/property/ttypes.py
concrete/search/FeedbackService.py
concrete/search/SearchProxyService.py
concrete/search/SearchService.py
concrete/search/__init__.py
concrete-4.18.2.dist-info/AUTHORS
concrete-4.18.2.dist-info/LICENSE
concrete-4.18.2.dist-info/METADATA
concrete-4.18.2.dist-info/WHEEL
concrete-4.18.2.dist-info/top_level.txt
concrete-4.18.2.dist-info/RECORD
